Metadata-Version: 1.0
Name: ani-donut
Version: 0.1.1
Summary: Python package to print donut.
Home-page: UNKNOWN
Author: Ani Marutyan
Author-email: ani_marutyan@edu.aua.am
License: MIT
Platform: UNKNOWN
